[
    {
        "variant": "N501Y",
        "cp": 221,
        "vp": 125,
        "phase3": 58,
        "structure": 32
    },
    {
        "variant": "E484K",
        "cp": 179,
        "vp": 94,
        "phase3": 71,
        "structure": 26
    },
    {
        "variant": "K417N",
        "cp": 131,
        "vp": 77,
        "phase3": 45,
        "structure": 26
    },
    {
        "variant": "K417T",
        "cp": 29,
        "vp": 0,
        "phase3": 6,
        "structure": 3
    },
    {
        "variant": "L452R",
        "cp": 42,
        "vp": 25,
        "phase3": 21,
        "structure": 6
    },
    {
        "variant": "Other individual mutations",
        "cp": 737,
        "vp": 556,
        "phase3": 785,
        "structure": 589
    },
    {
        "variant": "All individual mutations",
        "cp": 1154,
        "vp": 851,
        "phase3": 959,
        "structure": 671
    },
    {
        "variant": "B.1.1.7",
        "cp": 901,
        "vp": 1087,
        "phase3": 103,
        "structure": 58
    },
    {
        "variant": "B.1.351",
        "cp": 965,
        "vp": 1039,
        "phase3": 94,
        "structure": 42
    },
    {
        "variant": "P.1",
        "cp": 265,
        "vp": 277,
        "phase3": 33,
        "structure": 8
    },
    {
        "variant": "B.1.427/9",
        "cp": 60,
        "vp": 207,
        "phase3": 11,
        "structure": 7
    },
    {
        "variant": "B.1.526",
        "cp": 60,
        "vp": 105,
        "phase3": 12,
        "structure": 2
    },
    {
        "variant": "Other combinations of mutations",
        "cp": 1193,
        "vp": 855,
        "phase3": 227,
        "structure": 198
    },
    {
        "variant": "All combinations of mutations",
        "cp": 3558,
        "vp": 3587,
        "phase3": 496,
        "structure": 323
    }
]